[
  {
    "timestamp": "2026-04-25T09:01:01.491562",
    "reward": -0.17800000000000002,
    "incident_count": 5,
    "response_time": 1.9177017632974467,
    "overflow": false,
    "efficiency": 100,
    "fairness": 100,
    "survival": 55.73240193169505,
    "hospital_deliveries": 0,
    "hospital_occupancy": 1.3333333333333335
  },
  {
    "timestamp": "2026-04-25T09:01:02.492101",
    "reward": 9.742,
    "incident_count": 0,
    "response_time": 1.080385227140785,
    "overflow": false,
    "efficiency": 0,
    "fairness": 100,
    "survival": 35.73240193169505,
    "hospital_deliveries": 2,
    "hospital_occupancy": 2.666666666666667
  },
  {
    "timestamp": "2026-04-25T09:01:03.494266",
    "reward": -0.166,
    "incident_count": 3,
    "response_time": 1.3236585183128349,
    "overflow": false,
    "efficiency": 50.0,
    "fairness": 100,
    "survival": 52.74485519281201,
    "hospital_deliveries": 0,
    "hospital_occupancy": 3.3333333333333335
  },
  {
    "timestamp": "2026-04-25T09:01:04.493837",
    "reward": -0.126,
    "incident_count": 4,
    "response_time": 2.278113094804182,
    "overflow": false,
    "efficiency": 100,
    "fairness": 100,
    "survival": 59.54653251401421,
    "hospital_deliveries": 0,
    "hospital_occupancy": 4.0
  },
  {
    "timestamp": "2026-04-25T09:01:05.490784",
    "reward": 9.742,
    "incident_count": 3,
    "response_time": 3.268297528019625,
    "overflow": false,
    "efficiency": 0,
    "fairness": 100,
    "survival": 34.042950984260074,
    "hospital_deliveries": 2,
    "hospital_occupancy": 5.333333333333334
  },
  {
    "timestamp": "2026-04-25T09:01:06.496744",
    "reward": -0.17,
    "incident_count": 0,
    "response_time": 2.898997225182864,
    "overflow": false,
    "efficiency": 50.0,
    "fairness": 100,
    "survival": 51.35141339620052,
    "hospital_deliveries": 0,
    "hospital_occupancy": 6.0
  },
  {
    "timestamp": "2026-04-25T09:01:07.493643",
    "reward": 4.878000000000001,
    "incident_count": 0,
    "response_time": 1.432558970828524,
    "overflow": false,
    "efficiency": 50.0,
    "fairness": 100,
    "survival": 69.66703886764924,
    "hospital_deliveries": 1,
    "hospital_occupancy": 7.000000000000001
  },
  {
    "timestamp": "2026-04-25T09:01:08.498940",
    "reward": 4.98,
    "incident_count": 0,
    "response_time": 4.553536920615356,
    "overflow": false,
    "efficiency": 50.0,
    "fairness": 100,
    "survival": 100.0,
    "hospital_deliveries": 1,
    "hospital_occupancy": 8.0
  },
  {
    "timestamp": "2026-04-25T09:01:09.490419",
    "reward": 4.992,
    "incident_count": 3,
    "response_time": 3.765381591245538,
    "overflow": false,
    "efficiency": 0,
    "fairness": 100,
    "survival": 100.0,
    "hospital_deliveries": 1,
    "hospital_occupancy": 9.0
  },
  {
    "timestamp": "2026-04-25T09:01:10.491142",
    "reward": -0.007999999999999998,
    "incident_count": 0,
    "response_time": 2.1116439710826853,
    "overflow": false,
    "efficiency": 0,
    "fairness": 100,
    "survival": 100.0,
    "hospital_deliveries": 0,
    "hospital_occupancy": 9.666666666666666
  },
  {
    "timestamp": "2026-04-25T09:01:11.491866",
    "reward": -0.004000000000000001,
    "incident_count": 0,
    "response_time": 1.4161744934002884,
    "overflow": false,
    "efficiency": 0,
    "fairness": 100,
    "survival": 100.0,
    "hospital_deliveries": 0,
    "hospital_occupancy": 10.333333333333334
  },
  {
    "timestamp": "2026-04-25T09:01:12.491996",
    "reward": 0.0,
    "incident_count": 0,
    "response_time": 4.266642116291617,
    "overflow": false,
    "efficiency": 0,
    "fairness": 100,
    "survival": 100.0,
    "hospital_deliveries": 0,
    "hospital_occupancy": 11.0
  },
  {
    "timestamp": "2026-04-25T09:01:13.492192",
    "reward": -0.004000000000000001,
    "incident_count": 3,
    "response_time": 4.346532180047589,
    "overflow": false,
    "efficiency": 0,
    "fairness": 100,
    "survival": 100.0,
    "hospital_deliveries": 0,
    "hospital_occupancy": 11.666666666666666
  },
  {
    "timestamp": "2026-04-25T09:01:14.491243",
    "reward": -0.004000000000000001,
    "incident_count": 3,
    "response_time": 4.036484983507419,
    "overflow": false,
    "efficiency": 0,
    "fairness": 100,
    "survival": 100.0,
    "hospital_deliveries": 0,
    "hospital_occupancy": 12.333333333333334
  },
  {
    "timestamp": "2026-04-25T09:01:15.490240",
    "reward": 0.0,
    "incident_count": 3,
    "response_time": 3.118280802708893,
    "overflow": false,
    "efficiency": 0,
    "fairness": 100,
    "survival": 100.0,
    "hospital_deliveries": 0,
    "hospital_occupancy": 13.0
  },
  {
    "timestamp": "2026-04-25T09:01:16.491356",
    "reward": -0.003999999999999998,
    "incident_count": 3,
    "response_time": 2.01394616963608,
    "overflow": false,
    "efficiency": 0,
    "fairness": 100,
    "survival": 100.0,
    "hospital_deliveries": 0,
    "hospital_occupancy": 13.666666666666666
  },
  {
    "timestamp": "2026-04-25T09:01:17.493962",
    "reward": -0.003999999999999998,
    "incident_count": 0,
    "response_time": 1.1618828266306425,
    "overflow": false,
    "efficiency": 0,
    "fairness": 100,
    "survival": 100.0,
    "hospital_deliveries": 0,
    "hospital_occupancy": 14.333333333333334
  },
  {
    "timestamp": "2026-04-25T09:01:18.496718",
    "reward": -0.008000000000000002,
    "incident_count": 0,
    "response_time": 3.564354374004969,
    "overflow": false,
    "efficiency": 0,
    "fairness": 100,
    "survival": 100.0,
    "hospital_deliveries": 0,
    "hospital_occupancy": 15.0
  },
  {
    "timestamp": "2026-04-25T09:01:19.496620",
    "reward": -0.012,
    "incident_count": 0,
    "response_time": 4.537681893086434,
    "overflow": false,
    "efficiency": 0,
    "fairness": 100,
    "survival": 100.0,
    "hospital_deliveries": 0,
    "hospital_occupancy": 15.666666666666668
  },
  {
    "timestamp": "2026-04-25T13:13:18.125556",
    "reward": -0.41400000000000003,
    "incident_count": 4,
    "response_time": 4.4163946107512135,
    "overflow": false,
    "efficiency": 0.0,
    "fairness": 0.0,
    "survival": 0.0,
    "hospital_deliveries": 0,
    "hospital_occupancy": 0.6666666666666667
  },
  {
    "timestamp": "2026-04-25T13:13:18.135149",
    "reward": -0.714,
    "incident_count": 0,
    "response_time": 3.9109498682478407,
    "overflow": false,
    "efficiency": 0.0,
    "fairness": 0.0,
    "survival": 0.0,
    "hospital_deliveries": 0,
    "hospital_occupancy": 0.6666666666666667
  },
  {
    "timestamp": "2026-04-25T13:13:18.152349",
    "reward": -0.264,
    "incident_count": 5,
    "response_time": 2.8849173970841684,
    "overflow": false,
    "efficiency": 0.0,
    "fairness": 0.0,
    "survival": 0.0,
    "hospital_deliveries": 0,
    "hospital_occupancy": 0.6666666666666667
  },
  {
    "timestamp": "2026-04-25T13:13:19.111678",
    "reward": 4.832000000000001,
    "incident_count": 3,
    "response_time": 2.5604183083364473,
    "overflow": false,
    "efficiency": 0.0,
    "fairness": 0.0,
    "survival": 0.0,
    "hospital_deliveries": 1,
    "hospital_occupancy": 1.6666666666666667
  },
  {
    "timestamp": "2026-04-25T13:13:19.125209",
    "reward": -0.474,
    "incident_count": 0,
    "response_time": 4.157443235082265,
    "overflow": false,
    "efficiency": 0.0,
    "fairness": 0.0,
    "survival": 0.0,
    "hospital_deliveries": 0,
    "hospital_occupancy": 1.3333333333333335
  },
  {
    "timestamp": "2026-04-25T13:13:19.136834",
    "reward": -0.17800000000000002,
    "incident_count": 0,
    "response_time": 1.8500437467932183,
    "overflow": false,
    "efficiency": 0.0,
    "fairness": 0.0,
    "survival": 0.0,
    "hospital_deliveries": 0,
    "hospital_occupancy": 1.3333333333333335
  },
  {
    "timestamp": "2026-04-25T13:13:20.111275",
    "reward": 4.8340000000000005,
    "incident_count": 0,
    "response_time": 4.0639778814529866,
    "overflow": false,
    "efficiency": 0.0,
    "fairness": 0.0,
    "survival": 0.0,
    "hospital_deliveries": 1,
    "hospital_occupancy": 2.666666666666667
  },
  {
    "timestamp": "2026-04-25T13:13:20.122321",
    "reward": 9.446000000000002,
    "incident_count": 0,
    "response_time": 2.6201858745623317,
    "overflow": false,
    "efficiency": 0.0,
    "fairness": 0.0,
    "survival": 0.0,
    "hospital_deliveries": 2,
    "hospital_occupancy": 2.666666666666667
  },
  {
    "timestamp": "2026-04-25T13:13:20.133431",
    "reward": 4.680000000000001,
    "incident_count": 7,
    "response_time": 2.3148619449592944,
    "overflow": false,
    "efficiency": 0.0,
    "fairness": 0.0,
    "survival": 0.0,
    "hospital_deliveries": 1,
    "hospital_occupancy": 2.3333333333333335
  },
  {
    "timestamp": "2026-04-25T13:13:21.110549",
    "reward": -0.07200000000000001,
    "incident_count": 0,
    "response_time": 2.485373880224721,
    "overflow": false,
    "efficiency": 0.0,
    "fairness": 0.0,
    "survival": 0.0,
    "hospital_deliveries": 0,
    "hospital_occupancy": 3.3333333333333335
  },
  {
    "timestamp": "2026-04-25T13:13:21.122481",
    "reward": -0.9640000000000002,
    "incident_count": 0,
    "response_time": 1.6143688772617417,
    "overflow": false,
    "efficiency": 0.0,
    "fairness": 0.0,
    "survival": 0.0,
    "hospital_deliveries": 0,
    "hospital_occupancy": 3.3333333333333335
  },
  {
    "timestamp": "2026-04-25T13:13:21.136154",
    "reward": 4.734,
    "incident_count": 6,
    "response_time": 2.917112699224643,
    "overflow": false,
    "efficiency": 0.0,
    "fairness": 0.0,
    "survival": 0.0,
    "hospital_deliveries": 1,
    "hospital_occupancy": 3.3333333333333335
  },
  {
    "timestamp": "2026-04-25T13:13:22.116537",
    "reward": 4.634,
    "incident_count": 4,
    "response_time": 3.2831502868900726,
    "overflow": false,
    "efficiency": 0.0,
    "fairness": 0.0,
    "survival": 0.0,
    "hospital_deliveries": 1,
    "hospital_occupancy": 4.333333333333334
  },
  {
    "timestamp": "2026-04-25T13:13:22.129059",
    "reward": -0.678,
    "incident_count": 9,
    "response_time": 2.2955945931670283,
    "overflow": false,
    "efficiency": 0.0,
    "fairness": 0.0,
    "survival": 0.0,
    "hospital_deliveries": 0,
    "hospital_occupancy": 4.0
  },
  {
    "timestamp": "2026-04-25T13:13:22.142249",
    "reward": -0.17600000000000002,
    "incident_count": 6,
    "response_time": 4.084568380037627,
    "overflow": false,
    "efficiency": 0.0,
    "fairness": 0.0,
    "survival": 0.0,
    "hospital_deliveries": 0,
    "hospital_occupancy": 4.0
  },
  {
    "timestamp": "2026-04-25T13:13:23.119242",
    "reward": 4.888000000000001,
    "incident_count": 0,
    "response_time": 4.594735164191159,
    "overflow": false,
    "efficiency": 0.0,
    "fairness": 0.0,
    "survival": 0.0,
    "hospital_deliveries": 1,
    "hospital_occupancy": 5.333333333333334
  },
  {
    "timestamp": "2026-04-25T13:13:23.132895",
    "reward": 9.242,
    "incident_count": 0,
    "response_time": 1.3392501410203157,
    "overflow": false,
    "efficiency": 0.0,
    "fairness": 0.0,
    "survival": 0.0,
    "hospital_deliveries": 2,
    "hospital_occupancy": 5.333333333333334
  },
  {
    "timestamp": "2026-04-25T13:13:23.145053",
    "reward": -0.222,
    "incident_count": 7,
    "response_time": 2.882873922808705,
    "overflow": false,
    "efficiency": 0.0,
    "fairness": 0.0,
    "survival": 0.0,
    "hospital_deliveries": 0,
    "hospital_occupancy": 4.666666666666667
  },
  {
    "timestamp": "2026-04-25T13:13:24.111107",
    "reward": -0.324,
    "incident_count": 5,
    "response_time": 3.2086418173133393,
    "overflow": false,
    "efficiency": 0.0,
    "fairness": 0.0,
    "survival": 0.0,
    "hospital_deliveries": 0,
    "hospital_occupancy": 6.0
  },
  {
    "timestamp": "2026-04-25T13:13:24.124539",
    "reward": -0.47000000000000003,
    "incident_count": 0,
    "response_time": 1.2962163270450588,
    "overflow": false,
    "efficiency": 0.0,
    "fairness": 0.0,
    "survival": 0.0,
    "hospital_deliveries": 0,
    "hospital_occupancy": 6.0
  },
  {
    "timestamp": "2026-04-25T13:13:24.138268",
    "reward": 4.686000000000001,
    "incident_count": 7,
    "response_time": 1.124626952023771,
    "overflow": false,
    "efficiency": 0.0,
    "fairness": 0.0,
    "survival": 0.0,
    "hospital_deliveries": 1,
    "hospital_occupancy": 5.666666666666666
  },
  {
    "timestamp": "2026-04-25T13:13:25.108716",
    "reward": 9.288,
    "incident_count": 0,
    "response_time": 3.982412682705379,
    "overflow": false,
    "efficiency": 0.0,
    "fairness": 0.0,
    "survival": 0.0,
    "hospital_deliveries": 2,
    "hospital_occupancy": 7.333333333333333
  },
  {
    "timestamp": "2026-04-25T13:13:25.127457",
    "reward": 4.736000000000001,
    "incident_count": 0,
    "response_time": 3.800999702527433,
    "overflow": false,
    "efficiency": 0.0,
    "fairness": 0.0,
    "survival": 0.0,
    "hospital_deliveries": 1,
    "hospital_occupancy": 7.000000000000001
  },
  {
    "timestamp": "2026-04-25T13:13:25.137852",
    "reward": 4.688000000000001,
    "incident_count": 7,
    "response_time": 3.1153719566862788,
    "overflow": false,
    "efficiency": 0.0,
    "fairness": 0.0,
    "survival": 0.0,
    "hospital_deliveries": 1,
    "hospital_occupancy": 6.666666666666667
  },
  {
    "timestamp": "2026-04-25T13:13:26.115504",
    "reward": -0.42000000000000004,
    "incident_count": 0,
    "response_time": 3.19799729315817,
    "overflow": false,
    "efficiency": 0.0,
    "fairness": 0.0,
    "survival": 0.0,
    "hospital_deliveries": 0,
    "hospital_occupancy": 8.0
  },
  {
    "timestamp": "2026-04-25T13:13:26.126201",
    "reward": -0.17600000000000002,
    "incident_count": 0,
    "response_time": 4.703617374294276,
    "overflow": false,
    "efficiency": 0.0,
    "fairness": 0.0,
    "survival": 0.0,
    "hospital_deliveries": 0,
    "hospital_occupancy": 7.666666666666666
  },
  {
    "timestamp": "2026-04-25T13:13:26.137519",
    "reward": 4.636000000000001,
    "incident_count": 8,
    "response_time": 2.090232769224636,
    "overflow": false,
    "efficiency": 0.0,
    "fairness": 0.0,
    "survival": 0.0,
    "hospital_deliveries": 1,
    "hospital_occupancy": 7.666666666666666
  },
  {
    "timestamp": "2026-04-25T13:13:27.115199",
    "reward": 4.724,
    "incident_count": 7,
    "response_time": 1.033534986282202,
    "overflow": false,
    "efficiency": 0.0,
    "fairness": 0.0,
    "survival": 0.0,
    "hospital_deliveries": 1,
    "hospital_occupancy": 9.0
  },
  {
    "timestamp": "2026-04-25T13:13:27.131648",
    "reward": 4.732,
    "incident_count": 0,
    "response_time": 2.0508349175447216,
    "overflow": false,
    "efficiency": 0.0,
    "fairness": 0.0,
    "survival": 0.0,
    "hospital_deliveries": 1,
    "hospital_occupancy": 8.666666666666668
  },
  {
    "timestamp": "2026-04-25T13:13:27.145280",
    "reward": 4.634,
    "incident_count": 8,
    "response_time": 2.1436356673611217,
    "overflow": false,
    "efficiency": 0.0,
    "fairness": 0.0,
    "survival": 0.0,
    "hospital_deliveries": 1,
    "hospital_occupancy": 8.666666666666668
  },
  {
    "timestamp": "2026-04-25T13:13:28.107670",
    "reward": 4.774,
    "incident_count": 0,
    "response_time": 4.572055681668473,
    "overflow": false,
    "efficiency": 0.0,
    "fairness": 0.0,
    "survival": 0.0,
    "hospital_deliveries": 1,
    "hospital_occupancy": 10.0
  },
  {
    "timestamp": "2026-04-25T13:13:28.128390",
    "reward": -0.17600000000000002,
    "incident_count": 0,
    "response_time": 2.6245260779910717,
    "overflow": false,
    "efficiency": 0.0,
    "fairness": 0.0,
    "survival": 0.0,
    "hospital_deliveries": 0,
    "hospital_occupancy": 9.333333333333334
  },
  {
    "timestamp": "2026-04-25T13:13:28.138896",
    "reward": 4.628000000000001,
    "incident_count": 0,
    "response_time": 3.8363954474927358,
    "overflow": false,
    "efficiency": 0.0,
    "fairness": 0.0,
    "survival": 0.0,
    "hospital_deliveries": 1,
    "hospital_occupancy": 9.666666666666666
  },
  {
    "timestamp": "2026-04-25T13:13:29.117128",
    "reward": -0.136,
    "incident_count": 0,
    "response_time": 4.545527266451407,
    "overflow": false,
    "efficiency": 0.0,
    "fairness": 0.0,
    "survival": 0.0,
    "hospital_deliveries": 0,
    "hospital_occupancy": 10.666666666666668
  },
  {
    "timestamp": "2026-04-25T13:13:29.132826",
    "reward": 9.748,
    "incident_count": 9,
    "response_time": 1.0492330607989002,
    "overflow": false,
    "efficiency": 0.0,
    "fairness": 0.0,
    "survival": 0.0,
    "hospital_deliveries": 2,
    "hospital_occupancy": 10.666666666666668
  },
  {
    "timestamp": "2026-04-25T13:13:29.148524",
    "reward": -0.532,
    "incident_count": 0,
    "response_time": 1.5474570462865995,
    "overflow": false,
    "efficiency": 0.0,
    "fairness": 0.0,
    "survival": 0.0,
    "hospital_deliveries": 0,
    "hospital_occupancy": 10.333333333333334
  },
  {
    "timestamp": "2026-04-25T13:13:30.107670",
    "reward": 9.784,
    "incident_count": 6,
    "response_time": 2.648728486023999,
    "overflow": false,
    "efficiency": 0.0,
    "fairness": 0.0,
    "survival": 0.0,
    "hospital_deliveries": 2,
    "hospital_occupancy": 12.0
  },
  {
    "timestamp": "2026-04-25T13:13:30.125685",
    "reward": -0.162,
    "incident_count": 9,
    "response_time": 4.0466627951506355,
    "overflow": false,
    "efficiency": 0.0,
    "fairness": 0.0,
    "survival": 0.0,
    "hospital_deliveries": 0,
    "hospital_occupancy": 11.333333333333332
  },
  {
    "timestamp": "2026-04-25T13:13:30.139496",
    "reward": -0.528,
    "incident_count": 9,
    "response_time": 3.0908242065577274,
    "overflow": false,
    "efficiency": 0.0,
    "fairness": 0.0,
    "survival": 0.0,
    "hospital_deliveries": 0,
    "hospital_occupancy": 11.0
  },
  {
    "timestamp": "2026-04-25T13:13:31.115195",
    "reward": -0.13,
    "incident_count": 6,
    "response_time": 1.4337323488286513,
    "overflow": false,
    "efficiency": 0.0,
    "fairness": 0.0,
    "survival": 0.0,
    "hospital_deliveries": 0,
    "hospital_occupancy": 12.666666666666668
  },
  {
    "timestamp": "2026-04-25T13:13:31.131256",
    "reward": -0.07400000000000001,
    "incident_count": 9,
    "response_time": 3.269970272199071,
    "overflow": false,
    "efficiency": 0.0,
    "fairness": 0.0,
    "survival": 0.0,
    "hospital_deliveries": 0,
    "hospital_occupancy": 12.0
  },
  {
    "timestamp": "2026-04-25T13:13:31.150420",
    "reward": 4.13,
    "incident_count": 0,
    "response_time": 1.7457719104019502,
    "overflow": false,
    "efficiency": 0.0,
    "fairness": 0.0,
    "survival": 0.0,
    "hospital_deliveries": 1,
    "hospital_occupancy": 12.0
  },
  {
    "timestamp": "2026-04-25T13:13:32.113675",
    "reward": 4.822000000000001,
    "incident_count": 0,
    "response_time": 3.624761436832887,
    "overflow": false,
    "efficiency": 0.0,
    "fairness": 0.0,
    "survival": 0.0,
    "hospital_deliveries": 1,
    "hospital_occupancy": 13.666666666666666
  },
  {
    "timestamp": "2026-04-25T13:13:32.130530",
    "reward": 4.840000000000001,
    "incident_count": 0,
    "response_time": 3.9527628830568093,
    "overflow": false,
    "efficiency": 0.0,
    "fairness": 0.0,
    "survival": 0.0,
    "hospital_deliveries": 1,
    "hospital_occupancy": 13.0
  },
  {
    "timestamp": "2026-04-25T13:13:32.145490",
    "reward": 4.380000000000001,
    "incident_count": 10,
    "response_time": 4.309094002007855,
    "overflow": false,
    "efficiency": 0.0,
    "fairness": 0.0,
    "survival": 0.0,
    "hospital_deliveries": 1,
    "hospital_occupancy": 13.0
  },
  {
    "timestamp": "2026-04-25T13:13:33.121780",
    "reward": -0.14200000000000002,
    "incident_count": 8,
    "response_time": 3.790443239413295,
    "overflow": false,
    "efficiency": 0.0,
    "fairness": 0.0,
    "survival": 0.0,
    "hospital_deliveries": 0,
    "hospital_occupancy": 14.333333333333334
  },
  {
    "timestamp": "2026-04-25T13:13:33.140958",
    "reward": 4.784,
    "incident_count": 0,
    "response_time": 3.9034406568813345,
    "overflow": false,
    "efficiency": 0.0,
    "fairness": 0.0,
    "survival": 0.0,
    "hospital_deliveries": 1,
    "hospital_occupancy": 14.000000000000002
  },
  {
    "timestamp": "2026-04-25T13:13:33.160047",
    "reward": -0.43200000000000005,
    "incident_count": 12,
    "response_time": 4.8767855960924855,
    "overflow": false,
    "efficiency": 0.0,
    "fairness": 0.0,
    "survival": 0.0,
    "hospital_deliveries": 0,
    "hospital_occupancy": 13.666666666666666
  },
  {
    "timestamp": "2026-04-25T13:13:34.114498",
    "reward": 4.57,
    "incident_count": 8,
    "response_time": 1.8089775575916915,
    "overflow": false,
    "efficiency": 0.0,
    "fairness": 0.0,
    "survival": 0.0,
    "hospital_deliveries": 1,
    "hospital_occupancy": 15.333333333333332
  },
  {
    "timestamp": "2026-04-25T13:13:34.135546",
    "reward": 4.830000000000001,
    "incident_count": 0,
    "response_time": 3.3214109696988863,
    "overflow": false,
    "efficiency": 0.0,
    "fairness": 0.0,
    "survival": 0.0,
    "hospital_deliveries": 1,
    "hospital_occupancy": 15.0
  },
  {
    "timestamp": "2026-04-25T13:13:34.153255",
    "reward": -0.436,
    "incident_count": 0,
    "response_time": 1.112514952527285,
    "overflow": false,
    "efficiency": 0.0,
    "fairness": 0.0,
    "survival": 0.0,
    "hospital_deliveries": 0,
    "hospital_occupancy": 14.333333333333334
  },
  {
    "timestamp": "2026-04-25T13:13:35.118827",
    "reward": 4.8180000000000005,
    "incident_count": 0,
    "response_time": 1.9556331282229489,
    "overflow": false,
    "efficiency": 0.0,
    "fairness": 0.0,
    "survival": 0.0,
    "hospital_deliveries": 1,
    "hospital_occupancy": 16.333333333333332
  },
  {
    "timestamp": "2026-04-25T13:13:35.141048",
    "reward": -0.384,
    "incident_count": 13,
    "response_time": 1.6278938201796032,
    "overflow": false,
    "efficiency": 0.0,
    "fairness": 0.0,
    "survival": 0.0,
    "hospital_deliveries": 0,
    "hospital_occupancy": 15.666666666666668
  },
  {
    "timestamp": "2026-04-25T13:13:35.156447",
    "reward": 4.526,
    "incident_count": 0,
    "response_time": 3.625221404451921,
    "overflow": false,
    "efficiency": 0.0,
    "fairness": 0.0,
    "survival": 0.0,
    "hospital_deliveries": 1,
    "hospital_occupancy": 15.333333333333332
  },
  {
    "timestamp": "2026-04-25T13:13:36.112175",
    "reward": 4.862000000000001,
    "incident_count": 0,
    "response_time": 2.823588286399607,
    "overflow": false,
    "efficiency": 0.0,
    "fairness": 0.0,
    "survival": 0.0,
    "hospital_deliveries": 1,
    "hospital_occupancy": 17.333333333333336
  },
  {
    "timestamp": "2026-04-25T13:13:36.129674",
    "reward": 9.532,
    "incident_count": 0,
    "response_time": 3.435658160308989,
    "overflow": false,
    "efficiency": 0.0,
    "fairness": 0.0,
    "survival": 0.0,
    "hospital_deliveries": 2,
    "hospital_occupancy": 17.0
  },
  {
    "timestamp": "2026-04-25T13:13:36.147119",
    "reward": -0.438,
    "incident_count": 0,
    "response_time": 3.1431064141035288,
    "overflow": false,
    "efficiency": 0.0,
    "fairness": 0.0,
    "survival": 0.0,
    "hospital_deliveries": 0,
    "hospital_occupancy": 16.0
  },
  {
    "timestamp": "2026-04-25T13:13:37.114684",
    "reward": 4.86,
    "incident_count": 8,
    "response_time": 2.3025169720620036,
    "overflow": false,
    "efficiency": 0.0,
    "fairness": 0.0,
    "survival": 0.0,
    "hospital_deliveries": 1,
    "hospital_occupancy": 18.333333333333332
  },
  {
    "timestamp": "2026-04-25T13:13:37.135245",
    "reward": -0.17400000000000002,
    "incident_count": 11,
    "response_time": 1.5030619216362777,
    "overflow": false,
    "efficiency": 0.0,
    "fairness": 0.0,
    "survival": 0.0,
    "hospital_deliveries": 0,
    "hospital_occupancy": 17.666666666666668
  },
  {
    "timestamp": "2026-04-25T13:13:37.169292",
    "reward": 4.422000000000001,
    "incident_count": 15,
    "response_time": 2.0429109806727745,
    "overflow": false,
    "efficiency": 0.0,
    "fairness": 0.0,
    "survival": 0.0,
    "hospital_deliveries": 1,
    "hospital_occupancy": 17.0
  },
  {
    "timestamp": "2026-04-25T13:13:55.389523",
    "reward": -0.21400000000000002,
    "incident_count": 0,
    "response_time": 1.012971768793543,
    "overflow": false,
    "efficiency": 50.0,
    "fairness": 100,
    "survival": 44.7247141726576,
    "hospital_deliveries": 0,
    "hospital_occupancy": 0.6666666666666667
  },
  {
    "timestamp": "2026-04-25T13:13:56.392024",
    "reward": 4.8340000000000005,
    "incident_count": 4,
    "response_time": 4.1126027323702985,
    "overflow": false,
    "efficiency": 50.0,
    "fairness": 100,
    "survival": 58.32808690316935,
    "hospital_deliveries": 1,
    "hospital_occupancy": 1.6666666666666667
  },
  {
    "timestamp": "2026-04-25T13:13:57.390679",
    "reward": -0.08,
    "incident_count": 4,
    "response_time": 1.563239560440548,
    "overflow": false,
    "efficiency": 100,
    "fairness": 100,
    "survival": 70.84452014803757,
    "hospital_deliveries": 0,
    "hospital_occupancy": 2.3333333333333335
  },
  {
    "timestamp": "2026-04-25T13:13:58.395309",
    "reward": -0.07600000000000001,
    "incident_count": 4,
    "response_time": 4.70726118800889,
    "overflow": false,
    "efficiency": 100,
    "fairness": 100,
    "survival": 70.84452014803757,
    "hospital_deliveries": 0,
    "hospital_occupancy": 3.0
  },
  {
    "timestamp": "2026-04-25T13:13:59.391278",
    "reward": 9.84,
    "incident_count": 0,
    "response_time": 2.2631303370932336,
    "overflow": false,
    "efficiency": 0,
    "fairness": 100,
    "survival": 58.344520148037574,
    "hospital_deliveries": 2,
    "hospital_occupancy": 4.333333333333334
  },
  {
    "timestamp": "2026-04-25T13:14:00.398322",
    "reward": -0.32,
    "incident_count": 3,
    "response_time": 4.2976031171464015,
    "overflow": false,
    "efficiency": 50.0,
    "fairness": 0,
    "survival": 56.68676864476046,
    "hospital_deliveries": 0,
    "hospital_occupancy": 5.0
  },
  {
    "timestamp": "2026-04-25T13:14:01.397356",
    "reward": -0.032,
    "incident_count": 3,
    "response_time": 4.591761547097773,
    "overflow": false,
    "efficiency": 100,
    "fairness": 100,
    "survival": 100.0,
    "hospital_deliveries": 0,
    "hospital_occupancy": 5.666666666666666
  },
  {
    "timestamp": "2026-04-25T13:14:02.398059",
    "reward": 4.984,
    "incident_count": 0,
    "response_time": 3.7209431907616373,
    "overflow": false,
    "efficiency": 50.0,
    "fairness": 100,
    "survival": 100.0,
    "hospital_deliveries": 1,
    "hospital_occupancy": 6.666666666666667
  },
  {
    "timestamp": "2026-04-25T13:14:03.394384",
    "reward": -0.018,
    "incident_count": 2,
    "response_time": 3.9532532101406894,
    "overflow": false,
    "efficiency": 50.0,
    "fairness": 100,
    "survival": 100.0,
    "hospital_deliveries": 0,
    "hospital_occupancy": 7.333333333333333
  },
  {
    "timestamp": "2026-04-25T13:14:04.395311",
    "reward": 4.994,
    "incident_count": 1,
    "response_time": 1.2696644616630541,
    "overflow": false,
    "efficiency": 0,
    "fairness": 100,
    "survival": 100.0,
    "hospital_deliveries": 1,
    "hospital_occupancy": 8.333333333333332
  },
  {
    "timestamp": "2026-04-25T13:14:05.398031",
    "reward": -0.009999999999999998,
    "incident_count": 1,
    "response_time": 2.699496610797186,
    "overflow": false,
    "efficiency": 0,
    "fairness": 100,
    "survival": 100.0,
    "hospital_deliveries": 0,
    "hospital_occupancy": 9.0
  },
  {
    "timestamp": "2026-04-25T13:14:06.395781",
    "reward": -0.009999999999999998,
    "incident_count": 0,
    "response_time": 1.9926990273962053,
    "overflow": false,
    "efficiency": 0,
    "fairness": 100,
    "survival": 100.0,
    "hospital_deliveries": 0,
    "hospital_occupancy": 9.666666666666666
  },
  {
    "timestamp": "2026-04-25T13:14:07.395355",
    "reward": -0.014000000000000002,
    "incident_count": 0,
    "response_time": 2.654658909238618,
    "overflow": false,
    "efficiency": 0,
    "fairness": 100,
    "survival": 100.0,
    "hospital_deliveries": 0,
    "hospital_occupancy": 10.333333333333334
  },
  {
    "timestamp": "2026-04-25T13:14:08.394554",
    "reward": -0.16000000000000003,
    "incident_count": 0,
    "response_time": 1.182889283257683,
    "overflow": false,
    "efficiency": 0,
    "fairness": 100,
    "survival": 58.27610519430003,
    "hospital_deliveries": 0,
    "hospital_occupancy": 11.0
  },
  {
    "timestamp": "2026-04-25T13:14:09.394652",
    "reward": -0.11800000000000001,
    "incident_count": 0,
    "response_time": 4.005683197186672,
    "overflow": false,
    "efficiency": 50.0,
    "fairness": 100,
    "survival": 69.0530085899048,
    "hospital_deliveries": 0,
    "hospital_occupancy": 11.666666666666666
  },
  {
    "timestamp": "2026-04-25T13:14:10.391802",
    "reward": 4.976,
    "incident_count": 0,
    "response_time": 4.230949727918189,
    "overflow": false,
    "efficiency": 50.0,
    "fairness": 100,
    "survival": 100.0,
    "hospital_deliveries": 1,
    "hospital_occupancy": 12.666666666666668
  },
  {
    "timestamp": "2026-04-25T13:14:11.391559",
    "reward": -0.324,
    "incident_count": 0,
    "response_time": 4.765738230252422,
    "overflow": false,
    "efficiency": 50.0,
    "fairness": 0,
    "survival": 64.78584468081962,
    "hospital_deliveries": 0,
    "hospital_occupancy": 13.333333333333334
  },
  {
    "timestamp": "2026-04-25T13:14:12.391939",
    "reward": -0.034,
    "incident_count": 4,
    "response_time": 3.0888753350422973,
    "overflow": false,
    "efficiency": 100,
    "fairness": 100,
    "survival": 100.0,
    "hospital_deliveries": 0,
    "hospital_occupancy": 14.000000000000002
  },
  {
    "timestamp": "2026-04-25T13:14:13.390031",
    "reward": 9.99,
    "incident_count": 2,
    "response_time": 4.393908707842095,
    "overflow": false,
    "efficiency": 0,
    "fairness": 100,
    "survival": 100.0,
    "hospital_deliveries": 2,
    "hospital_occupancy": 15.333333333333332
  },
  {
    "timestamp": "2026-04-25T13:14:14.389578",
    "reward": -0.009999999999999998,
    "incident_count": 2,
    "response_time": 1.7543572924821418,
    "overflow": false,
    "efficiency": 0,
    "fairness": 100,
    "survival": 100.0,
    "hospital_deliveries": 0,
    "hospital_occupancy": 16.0
  },
  {
    "timestamp": "2026-04-25T13:15:15.698138",
    "reward": -0.6140000000000001,
    "incident_count": 4,
    "response_time": 1.4809353111486154,
    "overflow": false,
    "efficiency": 50.0,
    "fairness": 33.333333333333336,
    "survival": 41.52969217998621,
    "hospital_deliveries": 0,
    "hospital_occupancy": 0.6666666666666667
  }
]